hyqcopt/__init__.py
hyqcopt/api.py
hyqcopt/config.py
hyqcopt/factory.py
hyqcopt/interface.py
hyqcopt/algorithms/__init__.py
hyqcopt/algorithms/distributed.py
hyqcopt/algorithms/grover.py
hyqcopt/algorithms/qaoa.py
hyqcopt/backends/__init__.py
hyqcopt/backends/qiskit.py
hyqcopt/benchmarking/comparative.py
hyqcopt/classical/__init__.py
hyqcopt/classical/optimizers.py
hyqcopt/classical/metaheuristics/__init__.py
hyqcopt/core/exceptions.py
hyqcopt/core/interfaces.py
hyqcopt/problems/__init__.py
hyqcopt/problems/combinatorial/__init__.py
hyqcopt/problems/combinatorial/maxcut.py
hyqcopt/problems/combinatorial/tsp.py
hyqcopt/problems/continuous/__init__.py
hyqcopt/utils/converters.py
hyqcopt-0.1.0.dist-info/LICENSE
hyqcopt-0.1.0.dist-info/METADATA
hyqcopt-0.1.0.dist-info/WHEEL
hyqcopt-0.1.0.dist-info/top_level.txt
hyqcopt-0.1.0.dist-info/RECORD
