Metadata-Version: 2.2
Name: hyqcopt
Version: 0.1.0
Summary: Hybrid Quantum-Classical Optimization Framework
Author-email: Krishna Bajpai <bajpaikrishna715@gmail.com>
License: Apache-2.0
Project-URL: Homepage, https://github.com/yourusername/hyqcopt
Project-URL: Documentation, https://hyqcopt.readthedocs.io
Classifier: Development Status :: 3 - Alpha
Classifier: Intended Audience :: Science/Research
Classifier: Topic :: Scientific/Engineering
Classifier: License :: OSI Approved :: Apache Software License
Classifier: Programming Language :: Python :: 3.9
Requires-Python: >=3.8
License-File: LICENSE
Requires-Dist: numpy>=1.21
Requires-Dist: scipy>=1.7
Requires-Dist: pandas>=1.3
Requires-Dist: matplotlib>=3.4
Provides-Extra: qiskit
Requires-Dist: qiskit>=0.44; extra == "qiskit"
Requires-Dist: qiskit-aer>=0.12; extra == "qiskit"
Provides-Extra: pennylane
Requires-Dist: pennylane>=0.32; extra == "pennylane"
Requires-Dist: pennylane-qiskit>=0.32; extra == "pennylane"
Provides-Extra: braket
Requires-Dist: amazon-braket-sdk>=1.35; extra == "braket"
Provides-Extra: dev
Requires-Dist: pytest>=7.0; extra == "dev"
Requires-Dist: pytest-cov>=4.0; extra == "dev"
Requires-Dist: mypy>=1.0; extra == "dev"
Requires-Dist: flake8>=5.0; extra == "dev"
